apifactory/__init__.py
apifactory/service.py
py_apifactory-0.1.1.dist-info/licenses/LICENSE.md
py_apifactory-0.1.1.dist-info/METADATA
py_apifactory-0.1.1.dist-info/WHEEL
py_apifactory-0.1.1.dist-info/top_level.txt
py_apifactory-0.1.1.dist-info/RECORD
